{
    "title": "The Shawshank Redemption 1994",
    "description": "حين يُتّهم بقتل زوجته وعشيقها، يحاول موظّف بنك رزين النجاة في السجن عن طريق التمسّك بالأمل… وتكوين صداقة مع (ريد)، زميله السجين مدى الحياة.",
    "video_url": "https://nikaplayerr.com/embed/netuhzts64re",
    "image_url": "https://www.canva.com/design/DAGdPhJqu_8/O71V4qTOqjWT5TsNR3R1mQ/view?utm_content=DAGdPhJqu_8&utm_campaign=designshare&utm_medium=link2&utm_source=uniquelinks&utlId=h810f6252c5",
    "rating": 1.5,
    "year": 2021
}
